{"list":[
    {"no":"1","name":"生まれ変わる者","img":"0001_F","class":"F","kind":"無","previous":"","use":["転生の鍵"],"S":"15","A":"4.5","D":"5","L":"1"},
    {"no":"2","name":"さなぎ","img":"0002_F","class":"F","kind":"無","previous":"","use":["幻獣の繭"],"S":"14","A":"4","D":"4.5","L":"1"},
    {"no":"3","name":"ケットシー","img":"0003_F","class":"F","kind":"獣","previous":["1","2"],"use":["旅立ちの剣"],"S":"15.5","A":"5.4","D":"5.5","L":"1"},
    {"no":"4","name":"ゲド","img":"0004_F","class":"F","kind":"魔","previous":["1","2"],"use":["悪魔の心"],"S":"15","A":"6.2","D":"4.8","L":"1"},
    {"no":"5","name":"付喪神","img":"0005_F","class":"F","kind":"霊","previous":["1","2"],"use":["思い出の切れ端"],"S":"18","A":"4.8","D":"5.2","L":"1"},
    {"no":"6","name":"幼竜","img":"0006_F","class":"F","kind":"龍","previous":"1","use":["ひときわ大きな卵"],"S":"16","A":"6.5","D":"4.5","L":"1"},
    {"no":"139","name":"さなぎ(queen)","img":"0139_F","class":"F","kind":"無","previous":"","use":["幻獣の繭"],"S":"15","A":"4.4","D":"5.4","L":"1.4"},

    {"no":"7","name":"ウミウシ","img":"0007_E","class":"E","kind":"霊","previous":"5","use":["海色の石"],"S":"21","A":"5.7","D":"5.35","L":"1"},
    {"no":"8","name":"オオカミ","img":"0008_E","class":"E","kind":"獣","previous":"3","use":["新鮮獣肉"],"S":"16.5","A":"6.2","D":"6.3","L":"1"},
    {"no":"9","name":"案山子神","img":"0009_E","class":"E","kind":"霊","previous":"5","use":["かかし棒"],"S":"19","A":"5.9","D":"5.8","L":"1"},
    {"no":"10","name":"グレムリン","img":"0010_E","class":"E","kind":"魔","previous":"4","use":["汚い古水"],"S":"16.5","A":"7","D":"5.5","L":"1"},
    {"no":"11","name":"原始竜","img":"0011_E","class":"E","kind":"龍","previous":"6","use":["原始の果実"],"S":"18","A":"7","D":"5.6","L":"1"},
    {"no":"12","name":"狐物異","img":"0012_E","class":"E","kind":"魔","previous":"4","use":["黒焦げた丸焼き"],"S":"15.5","A":"7.2","D":"5.7","L":"1"},
    {"no":"13","name":"サボクサー","img":"0013_E","class":"E","kind":"霊","previous":"5","use":["サボテンの乾皮"],"S":"19","A":"6.5","D":"5.2","L":"1"},
    {"no":"14","name":"彷徨う精霊","img":"0014_E","class":"E","kind":"霊","previous":"5","use":["消せない蝋燭"],"S":"20","A":"5.6","D":"5.8","L":"1"},
    {"no":"15","name":"スケルトン","img":"0015_E","class":"E","kind":"魔","previous":"4","use":["狂気の包丁"],"S":"16","A":"6.8","D":"5.9","L":"1"},
    {"no":"16","name":"ネコマタ","img":"0016_E","class":"E","kind":"獣","previous":"3","use":["マタタビの実"],"S":"17","A":"5.9","D":"6.5","L":"1"},
    {"no":"140","name":"遅咲蝶","img":"0140_E","class":"E","kind":"地","previous":["1","2","139"],"use":["金色的鱗粉"],"S":"16","A":"4.2","D":"6.17","L":"1"},

    {"no":"17","name":"火炎樹","img":"0017_D","class":"D","kind":"霊","previous":"13","use":["呪われた炎"],"S":"24","A":"6.2","D":"5.8","L":"1"},
    {"no":"18","name":"桂男","img":"0018_D","class":"D","kind":"霊","previous":["7","14"],"use":["誰かの草履"],"S":"22","A":"6.3","D":"6.4","L":"1"},
    {"no":"19","name":"キマイラ","img":"0019_D","class":"D","kind":"獣","previous":"16","use":["合成獣の石板"],"S":"18","A":"7","D":"7","L":"1"},
    {"no":"20","name":"狂骨","img":"0020_D","class":"D","kind":"魔","previous":["5","6"],"use":["邪悪な煙"],"S":"17","A":"8","D":"6.4","L":"1"},
    {"no":"21","name":"虎狼狸","img":"0021_D","class":"D","kind":"獣","previous":["8","10"],"use":["狂気の煙"],"S":"17.5","A":"7.2","D":"7","L":"1"},
    {"no":"22","name":"ケイブスパイダー","img":"0022_D","class":"D","kind":"魔","previous":["12","15"],"use":["黒く丸い瞳"],"S":"16.5","A":"8","D":"6.5","L":"1"},
    {"no":"23","name":"蒼翼竜","img":"0023_D","class":"D","kind":"龍","previous":"11","use":["異種族の石板"],"S":"19.8","A":"8.1","D":"6.2","L":"1"},
    {"no":"24","name":"ダークコブラ","img":"0024_D","class":"D","kind":"魔","previous":["12","15"],"use":["臭い毒液"],"S":"16.5","A":"8.2","D":"6.3","L":"1"},
    {"no":"25","name":"ドゥームビートル","img":"0025_D","class":"D","kind":"地","previous":"7","use":["蟲プリン"],"S":"18","A":"7.5","D":"6.5","L":"1"},
    {"no":"26","name":"ドライアド","img":"0026_D","class":"D","kind":"霊","previous":["9","13"],"use":["草模様の精霊石"],"S":"23","A":"6","D":"6.4","L":"1"},
    {"no":"27","name":"白虎","img":"0027_D","class":"D","kind":"獣","previous":["8","16"],"use":["真っ白な牙"],"S":"18","A":"7.1","D":"6.9","L":"1"},
    {"no":"28","name":"マミー","img":"0028_D","class":"D","kind":"霊","previous":["9","14"],"use":["水溶性の包帯"],"S":"22.5","A":"6.9","D":"5.6","L":"1"},
    {"no":"141","name":"小姫蜂","img":"0141_D","class":"D","kind":"地","previous":"140","use":["華的蜜"],"S":"18.5","A":"5.6","D":"8.4","L":"1"},

    {"no":"29","name":"アックスビーク","img":"0029_C","class":"C","kind":"獣","previous":["19","21"],"use":["巨大鳥の羽根"],"S":"20","A":"8.1","D":"8.3","L":"1"},
    {"no":"30","name":"インサーニア","img":"0030_C","class":"C","kind":"魔","previous":["20","28"],"use":["邪悪な首飾り"],"S":"18.5","A":"9.25","D":"7.6","L":"1"},
    {"no":"31","name":"ヴァンパイア","img":"0031_C","class":"C","kind":"魔","previous":["20","18"],"use":["悪魔の血"],"S":"18.5","A":"9.35","D":"7.5","L":"1"},
    {"no":"32","name":"馬魔","img":"0032_C","class":"C","kind":"獣","previous":"27","use":["和人形"],"S":"19","A":"8.3","D":"8.4","L":"1"},
    {"no":"33","name":"巨大クラブ","img":"0033_C","class":"C","kind":"地","previous":["22","25"],"use":["海に彷徨う泡"],"S":"19.5","A":"8","D":"8.5","L":"1"},
    {"no":"34","name":"清姫","img":"0034_C","class":"C","kind":"魔","previous":"24","use":["純真なこころ"],"S":"19","A":"9.4","D":"7.3","L":"1"},
    {"no":"35","name":"グリンブルスティ","img":"0035_C","class":"C","kind":"獣","previous":["19","27"],"use":["神秘的な大牙"],"S":"19.5","A":"8.4","D":"8.1","L":"1"},
    {"no":"36","name":"グレートマンティス","img":"0036_C","class":"C","kind":"地","previous":"25","use":["量産型増強剤"],"S":"17","A":"8.9","D":"8.45","L":"1"},
    {"no":"37","name":"コロポックル","img":"0037_C","class":"C","kind":"霊","previous":"26","use":["大きな蕗の傘"],"S":"24","A":"7.3","D":"7.7","L":"1"},
    {"no":"38","name":"ジョカ","img":"0038_C","class":"C","kind":"魔","previous":["22","24"],"use":["創造するこころ"],"S":"19.5","A":"8.7","D":"7.8","L":"1"},
    {"no":"39","name":"大地の精霊","img":"0039_C","class":"C","kind":"霊","previous":"28","use":["大地の精霊石"],"S":"22.5","A":"8","D":"7.5","L":"1"},
    {"no":"40","name":"バロン","img":"0040_C","class":"C","kind":"獣","previous":"21","use":["からくり歯車"],"S":"20","A":"7.9","D":"8.45","L":"1"},
    {"no":"41","name":"ヒメボタル","img":"0041_C","class":"C","kind":"霊","previous":"26","use":["川縁の光り"],"S":"25.55","A":"7.75","D":"7.5","L":"1.2"},
    {"no":"42","name":"ヘビードラゴン","img":"0042_C","class":"C","kind":"龍","previous":"23","use":["やみつき肉"],"S":"21.9","A":"9.2","D":"8.4","L":"1"},
    {"no":"43","name":"マイティーオーク","img":"0043_C","class":"C","kind":"地","previous":["17","26"],"use":["マナの塊"],"S":"21","A":"7.85","D":"8.15","L":"1"},
    {"no":"44","name":"魔術師ジョゼ","img":"0044_C","class":"C","kind":"霊","previous":"18","use":["魔力の源石"],"S":"23","A":"8.55","D":"6.8","L":"1"},
    {"no":"45","name":"ラヴァゴーレム","img":"0045_C","class":"C","kind":"地","previous":"17","use":["灼熱の溶岩"],"S":"19","A":"7.9","D":"8.8","L":"1"},
    {"no":"46","name":"霊界の魔女","img":"0046_C","class":"C","kind":"霊","previous":"26","use":["霊力の源石"],"S":"23","A":"7.55","D":"7.8","L":"1"},
    {"no":"47","name":"ワイバーン","img":"0047_C","class":"C","kind":"龍","previous":["36","23"],"use":["翼竜の置物"],"S":"19","A":"9.7","D":"8","L":"1"},
    {"no":"142","name":"精霊虫","img":"0142_C","class":"C","kind":"地","previous":"141","use":["世界樹的葉"],"S":"22","A":"6.38","D":"9.49","L":"1"},

    {"no":"48","name":"磯姫","img":"0048_B","class":"B","kind":"魔","previous":["38","46"],"use":["血を吸う長髪"],"S":"23","A":"10.3","D":"9.05","L":"1"},
    {"no":"49","name":"以津真天","img":"0049_B","class":"B","kind":"魔","previous":["38","40"],"use":["異国の漢方薬"],"S":"23.5","A":"10.25","D":"8.9","L":"1"},
    {"no":"50","name":"イーラ","img":"0050_B","class":"B","kind":"龍","previous":"30","use":["狂気の実"],"S":"24","A":"10.8","D":"8.9","L":"1"},
    {"no":"51","name":"桜花の精霊","img":"0051_B","class":"B","kind":"霊","previous":"37","use":["枯れない桜枝"],"S":"33","A":"8","D":"8","L":"1"},
    {"no":"52","name":"奥女中","img":"0052_B","class":"B","kind":"獣","previous":["32","34"],"use":["真心桜餅"],"S":"24","A":"9.3","D":"9.7","L":"1"},
    {"no":"53","name":"九尾","img":"0053_B","class":"B","kind":"獣","previous":["35","39"],"use":["きゅうり"],"S":"25.5","A":"8.55","D":"9.95","L":"1"},
    {"no":"54","name":"朽ちた堕天使","img":"0054_B","class":"B","kind":"魔","previous":["29","31"],"use":["邪悪な羽根"],"S":"23","A":"10.5","D":"8.85","L":"1"},
    {"no":"55","name":"グランドゴーレム","img":"0055_B","class":"B","kind":"地","previous":["43","45"],"use":["超化丸薬"],"S":"26.5","A":"8.7","D":"9.5","L":"1"},
    {"no":"56","name":"ケモノリュウ","img":"0056_B","class":"B","kind":"獣","previous":"29","use":["竜の血"],"S":"24.5","A":"9.3","D":"9.55","L":"1"},
    {"no":"57","name":"ケルベロス","img":"0057_B","class":"B","kind":"獣","previous":["35","40"],"use":["猛獣ステーキ"],"S":"24","A":"9.2","D":"9.8","L":"1"},
    {"no":"58","name":"幻影","img":"0058_B","class":"B","kind":"霊","previous":"46","use":["幻と影の種"],"S":"36","A":"7.3","D":"7.7","L":"1"},
    {"no":"59","name":"水竜","img":"0059_B","class":"B","kind":"龍","previous":["33","47"],"use":["潮騒の貝殻"],"S":"26","A":"11","D":"8.7","L":"1"},
    {"no":"60","name":"大海の精霊","img":"0060_B","class":"B","kind":"霊","previous":["44","46"],"use":["大海の精霊石"],"S":"32","A":"8.25","D":"8.1","L":"1"},
    {"no":"61","name":"デュラハン","img":"0061_B","class":"B","kind":"魔","previous":["32","30","46"],"use":["予言書"],"S":"22.5","A":"10.4","D":"9.1","L":"1"},
    {"no":"62","name":"ドラグーン","img":"0062_B","class":"B","kind":"龍","previous":["47","42"],"use":["黒炎の結晶"],"S":"23","A":"12","D":"9.2","L":"1"},
    {"no":"63","name":"ランド・レイズ","img":"0063_B","class":"B","kind":"地","previous":"33","use":["深海の結晶"],"S":"25","A":"9.4","D":"9.3","L":"1"},
    {"no":"64","name":"リビングソード","img":"0064_B","class":"B","kind":"霊","previous":"17","use":["魔剣新書"],"S":"21","A":"12.5","D":"7.5","L":"1","ps":"*越級"},

    {"no":"65","name":"ヴァルキリーβ","img":"0065_A","class":"A","kind":"霊","previous":"39","use":["正義を誓う羽根"],"S":"34.5","A":"13","D":"7.3","L":"1","ps":"*越級"},
    {"no":"66","name":"ウンディーネ","img":"0066_A","class":"A","kind":"霊","previous":"63","use":["アクアマリン"],"S":"37","A":"9.4","D":"10.3","L":"1"},
    {"no":"67","name":"火車","img":"0067_A","class":"A","kind":"獣","previous":"56","use":["悪食の焔"],"S":"29.7","A":"11.5","D":"10.6","L":"1"},
    {"no":"68","name":"グランドタートル","img":"0068_A","class":"A","kind":"地","previous":"55","use":["大自然の力"],"S":"28.5","A":"8.5","D":"14","L":"1"},
    {"no":"69","name":"グレートベアー","img":"0069_A","class":"A","kind":"獣","previous":["57","56"],"use":["激化丸薬"],"S":"30.5","A":"10.35","D":"11.5","L":"1"},
    {"no":"70","name":"ゲンジボタル","img":"0070_A","class":"A","kind":"霊","previous":"41","use":["源氏の光り"],"S":"37.77","A":"9.99","D":"9.99","L":"1.2","ps":"*越級"},
    {"no":"71","name":"獣神","img":"0071_A","class":"A","kind":"獣","previous":"53","use":["狐神の仮面"],"S":"28.5","A":"9.6","D":"12.9","L":"1"},
    {"no":"72","name":"女郎蜘蛛","img":"0072_A","class":"A","kind":"魔","previous":["48","49"],"use":["女郎の魂"],"S":"27","A":"12.9","D":"10.1","L":"1"},
    {"no":"73","name":"シルフィード","img":"0073_A","class":"A","kind":"霊","previous":"51","use":["風を司る力"],"S":"36","A":"11","D":"9","L":"1"},
    {"no":"74","name":"水竜神","img":"0074_A","class":"A","kind":"龍","previous":"59","use":["潮騒の記憶"],"S":"32.5","A":"12.4","D":"10.7","L":"1"},
    {"no":"75","name":"妲己","img":"0075_A","class":"A","kind":"獣","previous":["52","53"],"use":["美しき者の仮面"],"S":"29.5","A":"10.3","D":"11.9","L":"1"},
    {"no":"76","name":"魂を狩る者","img":"0076_A","class":"A","kind":"魔","previous":"49","use":["魂の蓄壷"],"S":"24","A":"15.2","D":"8.8","L":"1"},
    {"no":"77","name":"デーモンローズ","img":"0077_A","class":"A","kind":"地","previous":"43","use":["悪魔の薔薇"],"S":"31","A":"12.15","D":"9.5","L":"1","ps":"*越級"},
    {"no":"78","name":"ナイトメア","img":"0078_A","class":"A","kind":"魔","previous":["57","61"],"use":["具現化した悪夢"],"S":"26","A":"12.9","D":"10.45","L":"1"},
    {"no":"79","name":"パンプキンころがし","img":"0079_A","class":"A","kind":"地","previous":"68","use":["カボチャマフィン"],"S":"17.9","A":"8","D":"18","L":"1"},
    {"no":"80","name":"フェニックス","img":"0080_A","class":"A","kind":"霊","previous":["50","58"],"use":["不死の力"],"S":"45","A":"8.7","D":"8.3","L":"1"},
    {"no":"81","name":"マッドデーモン","img":"0081_A","class":"A","kind":"魔","previous":["54","61"],"use":["サタンの羽根"],"S":"25","A":"14.5","D":"9.2","L":"1"},
    {"no":"82","name":"ヨルムンガルド","img":"0082_A","class":"A","kind":"龍","previous":"62","use":["巨蛇竜の細胞"],"S":"29","A":"15.3","D":"9.4","L":"1"},
    {"no":"83","name":"ラグナロク","img":"0083_A","class":"A","kind":"霊","previous":"64","use":["秘めたる真価"],"S":"19.5","A":"20","D":"5.5","L":"1"},
    {"no":"84","name":"リリス","img":"0084_A","class":"A","kind":"魔","previous":"54","use":["常闇の使者"],"S":"27.5","A":"13.9","D":"9.1","L":"1"},
    {"no":"85","name":"ロックイーター","img":"0085_A","class":"A","kind":"地","previous":"55","use":["岩喰獣の心臓"],"S":"26","A":"11.1","D":"12.25","L":"1"},
    {"no":"143","name":"鬼灯提灯","img":"0143_A","class":"A","kind":"地","previous":"142","use":["鬼燈的實"],"S":"32","A":"7","D":"13","L":"1","ps":"*越級"},

    {"no":"86","name":"疎まれし者","img":"0086_S","class":"S","kind":"龍","previous":"82","use":["異次元の魔手"],"S":"22.1","A":"16","D":"13.05","L":"1"},
    {"no":"87","name":"干将莫耶","img":"0087_S","class":"S","kind":"霊","previous":"83","use":["夫婦の絆"],"S":"22.5","A":"20.8","D":"11","L":"1"},
    {"no":"88","name":"葛之葉姫","img":"0088_S","class":"S","kind":"獣","previous":"75","use":["天体書筆"],"S":"33","A":"11.9","D":"13","L":"1"},
    {"no":"89","name":"グリフォン","img":"0089_S","class":"S","kind":"獣","previous":"57","use":["どんぐり"],"S":"30.8","A":"12.1","D":"13.4","L":"1","ps":"*越級"},
    {"no":"90","name":"サラマンダー","img":"0090_S","class":"S","kind":"地","previous":"85","use":["灼熱の瞳"],"S":"30.5","A":"13.9","D":"11","L":"1"},
    {"no":"91","name":"ジャッカロープ","img":"0091_S","class":"S","kind":"魔","previous":"48","use":["うさぎとげんえい"],"S":"30","A":"16.5","D":"9.5","L":"1","ps":"*越級"},
    {"no":"92","name":"獣王","img":"0092_S","class":"S","kind":"獣","previous":["67","78"],"use":["魔界を牛耳る力"],"S":"28","A":"13.1","D":"12.6","L":"1"},
    {"no":"93","name":"酒呑童子","img":"0093_S","class":"S","kind":"獣","previous":"69","use":["真の救世主"],"S":"31","A":"11.9","D":"12.8","L":"1"},
    {"no":"94","name":"死を告げる者","img":"0094_S","class":"S","kind":"無","previous":"58","use":["鎮魂の力"],"S":"29","A":"13.3","D":"13.3","L":"1","ps":"*越級"},
    {"no":"95","name":"ジン","img":"0095_S","class":"S","kind":"霊","previous":"73","use":["魔法のランプ"],"S":"37","A":"12","D":"11.5","L":"1"},
    {"no":"96","name":"朱雀","img":"0096_S","class":"S","kind":"霊","previous":"80","use":["炎帝の証"],"S":"45.5","A":"11","D":"8.9","L":"1"},
    {"no":"97","name":"テティス","img":"0097_S","class":"S","kind":"霊","previous":"66","use":["深海の涙"],"S":"40.5","A":"10.4","D":"11.8","L":"1"},
    {"no":"98","name":"ナイトオブローズ","img":"0098_S","class":"S","kind":"地","previous":"77","use":["薔薇の香水"],"S":"39","A":"13","D":"9","L":"1"},
    {"no":"99","name":"虹色の番竜","img":"0099_S","class":"S","kind":"龍","previous":"106","use":["虹彩色の水"],"S":"34","A":"14.5","D":"13.5","L":"1"},
    {"no":"100","name":"鵺","img":"0100_S","class":"S","kind":"魔","previous":"72","use":["紫煙の煙管"],"S":"34.4","A":"13.5","D":"10.9","L":"1"},
    {"no":"101","name":"呪亀","img":"0101_S","class":"S","kind":"魔","previous":"68","use":["魔神の亀壺"],"S":"29","A":"11.5","D":"14.3","L":"1"},
    {"no":"102","name":"フリームスルス","img":"0102_S","class":"S","kind":"霊","previous":"60","use":["スノードーム"],"S":"37.5","A":"10.89","D":"12.5","L":"1","ps":"*越級"},
    {"no":"103","name":"ベロニカの乙女","img":"0103_S","class":"S","kind":"?","previous":"65","use":["ベロニカ"],"S":"38","A":"16","D":"9.6","L":"1"},
    {"no":"104","name":"マインドフレア","img":"0104_S","class":"S","kind":"魔","previous":"76","use":["全てを操る力"],"S":"28","A":"16.1","D":"9.5","L":"1"},
    {"no":"105","name":"魔王","img":"0105_S","class":"S","kind":"魔","previous":["81","84"],"use":["魔の救世主"],"S":"29.3","A":"15.15","D":"10.1","L":"1"},
    {"no":"106","name":"ミズチ","img":"0106_S","class":"S","kind":"龍","previous":"74","use":["雲間の幻"],"S":"35","A":"13","D":"11","L":"1"},
    {"no":"107","name":"夜神","img":"0107_S","class":"S","kind":"獣","previous":"71","use":["闇夜織"],"S":"30.5","A":"10.3","D":"14.55","L":"1"},
    {"no":"108","name":"宿木","img":"0108_S","class":"S","kind":"地","previous":"77","use":["すり鉢"],"S":"24.5","A":"5.2","D":"5.2","L":"1","ps":"*可退回上階(デーモンローズ)"},
    {"no":"109","name":"夜色の番竜","img":"0109_S","class":"S","kind":"龍","previous":"106","use":["夜色のオーロラ"],"S":"30.7","A":"17.1","D":"11.3","L":"1"},
    {"no":"110","name":"竜王","img":"0110_S","class":"S","kind":"龍","previous":"82","use":["世界を司る力"],"S":"30.5","A":"15.3","D":"10.8","L":"1"},
    {"no":"137","name":"ポセイドン","img":"0137_S","class":"S","kind":"霊","previous":"66","use":["海王の車駕"],"S":"38.73","A":"12.29","D":"13.66","L":"1"},
    {"no":"138","name":"パンドラ","img":"0138_S","class":"S","kind":"霊","previous":"84","use":["天外の箱"],"S":"29.86","A":"10.89","D":"17.79","L":"1.1"},
    {"no":"144","name":"ベルゼブル","img":"0144_S","class":"S","kind":"地","previous":"143","use":["精靈的微笑"],"S":"39.81","A":"11.49","D":"15.09","L":"1"},
    {"no":"145","name":"デスコーピオン","img":"0145_S","class":"S","kind":"地","previous":"143","use":["禁じられた猛毒"],"S":"31","A":"17.86","D":"11","L":"1"},

    {"no":"111","name":"アンドロジナス","img":"0111_SS","class":"SS","kind":"地","previous":"98","use":["酒豪の酒樽"],"S":"40.8","A":"15.1","D":"11.6","L":"1"},
    {"no":"112","name":"大神実命","img":"0112_SS","class":"SS","kind":"地","previous":"108","use":["ももまもり"],"S":"41.2","A":"12.8","D":"14.14","L":"1"},
    {"no":"113","name":"春日神鹿","img":"0113_SS","class":"SS","kind":"獣","previous":"92","use":["榊ノ円鏡"],"S":"33.2","A":"13.6","D":"14.5","L":"1"},
    {"no":"114","name":"我来也・朧","img":"0114_SS","class":"SS","kind":"?","previous":"101","use":["煙術の巻・朧"],"S":"30.8","A":"14.5","D":"15.8","L":"1"},
    {"no":"115","name":"熾天使","img":"0115_SS","class":"SS","kind":"霊","previous":"96","use":["先陣を切る剣"],"S":"47.4","A":"13.2","D":"10.5","L":"1"},
    {"no":"116","name":"神龍","img":"0116_SS","class":"SS","kind":"龍","previous":"110","use":["神龍の魂"],"S":"31.5","A":"16.9","D":"11.4","L":"1"},
    {"no":"117","name":"ダークロード","img":"0117_SS","class":"SS","kind":"魔","previous":"105","use":["魔神の魂"],"S":"29.5","A":"17.7","D":"10.6","L":"1"},
    {"no":"118","name":"玉藻前","img":"0118_SS","class":"SS","kind":"獣","previous":"88","use":["妖艶な魂"],"S":"37","A":"13.05","D":"13.55","L":"1"},
    {"no":"119","name":"地を穿つ魔","img":"0119_SS","class":"SS","kind":"魔","previous":"101","use":["古のもの"],"S":"30.9?","A":"15.8","D":"14.5","L":"1"},
    {"no":"120","name":"月都之姫","img":"0120_SS","class":"SS","kind":"獣","previous":"107","use":["姫の願い"],"S":"35.9","A":"12.8","D":"14.15","L":"1"},
    {"no":"121","name":"時を統べる者","img":"0121_SS","class":"SS","kind":"無","previous":"94","use":["クロノス"],"S":"30","A":"15.6","D":"14.9","L":"1"},
    {"no":"122","name":"ハルモニア","img":"0122_SS","class":"SS","kind":"霊","previous":"97","use":["調和の音"],"S":"44.1","A":"12","D":"12.6","L":"1"},
    {"no":"123","name":"ファラク","img":"0123_SS","class":"SS","kind":"地","previous":"90","use":["地への祈り"],"S":"31.5","A":"14.7","D":"13.6","L":"1"},
    {"no":"124","name":"夜叉姫","img":"0124_SS","class":"SS","kind":"魔","previous":"107","use":["青の根付け"],"S":"32.1","A":"13.1","D":"15.1","L":"1"},
    {"no":"125","name":"ルシファー","img":"0125_SS","class":"SS","kind":"魔","previous":"104","use":["叛逆のスープ"],"S":"38.8","A":"16.9","D":"11.1","L":"1"},
    {"no":"126","name":"災いの根源","img":"0126_SS","class":"SS","kind":"龍","previous":"86","use":["破壊への誘い"],"S":"28.88","A":"12.8","D":"16.5","L":"1"},
    {"no":"130","name":"伊吹童子","img":"0130_SS","class":"SS","kind":"獣","previous":"93","use":["酒瓢"],"S":"32.4","A":"17.4","D":"15.6","L":"1"},
    {"no":"131","name":"王家の末路","img":"0131_SS","class":"SS","kind":"無","previous":"94","use":["栄光と没落"],"S":"33.33","A":"14.44","D":"14.44","L":"1"},
    {"no":"133","name":"鶴姫","img":"0133_SS","class":"SS","kind":"魔","previous":"100","use":["冥婚の契り"],"S":"42.79","A":"15.87","D":"13.33","L":"1"},
    {"no":"134","name":"アポロン","img":"0134_SS","class":"SS","kind":"霊","previous":"103","use":["眩い閃光"],"S":"50.8","A":"18.8","D":"16.3","L":"0.88"},
    {"no":"135","name":"戦風の皇女","img":"0135_SS","class":"SS","kind":"霊","previous":"95","use":["風と君の狭間"],"S":"39.6","A":"15.4","D":"12.6","L":"1"},
    {"no":"146","name":"破壊神","img":"0146_SS","class":"SS","kind":"魔","previous":"145","use":["破壊王の魂"],"S":"34.56","A":"22.22","D":"12.12","L":"1"},

    {"no":"127","name":"聖竜","img":"0127_SS+","class":"SS+","kind":"龍","previous":["116"],"use":["聖というもの"],"S":"34.5","A":"18.8","D":"10.9","L":"1"},
    {"no":"128","name":"ダークロードナイトメア","img":"0128_SS+","class":"SS+","kind":"魔","previous":["117"],"use":["闇と蹄"],"S":"32.22","A":"17.9","D":"11.4","L":"1"},
    {"no":"129","name":"闇竜","img":"0129_SS+","class":"SS+","kind":"龍","previous":["126"],"use":["闇というもの"],"S":"29.2","A":"19","D":"12.9","L":"0.5"},
    {"no":"132","name":"アヌビス","img":"0132_SS+","class":"SS+","kind":"無","previous":["131"],"use":["死者の書"],"S":"41","A":"16.5","D":"15.5","L":"1.02"},
    {"no":"136","name":"蒼緑滓鹿","img":"0136_SS+","class":"SS+","kind":"獣","previous":["113"],"use":["月光蝶"],"S":"36.2","A":"14.7","D":"14.9","L":"1"}
],{"no":"137","name":"ポセイドン","img":"0136_SS+","class":"SS+","kind":"獣","previous":["113"],"use":["月光蝶"],"S":"36.2","A":"14.7","D":"14.9","L":"1"}
"list2":[
    {"f":"3","e":"16","d":"19","c":"29","b":"54","a":"81","s":"105","ss":"117","sss":"128"},
    {"f":"3","e":"16","d":"19","c":"29","b":"54","a":"84","s":"105","ss":"117","sss":"128"},
    {"f":"3","e":"16","d":"19","c":"29","b":"54","a":"84","s":"138","ss":"","sss":""},
    {"f":"3","e":"16","d":"19","c":"29","b":"56","a":"67","s":"92","ss":"113","sss":"136"},
    {"f":"3","e":"16","d":"19","c":"29","b":"56","a":"69","s":"93","ss":"","sss":""},
    {"f":"3","e":"16","d":"19","c":"29","b":"57","a":"69","s":"93","ss":"","sss":""},
    {"f":"3","e":"16","d":"19","c":"29","b":"57","a":"78","s":"92","ss":"113","sss":"136"},
    {"f":"3","e":"16","d":"19","c":"29","b":"53","a":"89","s":"89","ss":"","sss":""},
    {"f":"3","e":"16","d":"19","c":"29","b":"53","a":"71","s":"107","ss":"120","sss":""},
    {"f":"3","e":"16","d":"19","c":"35","b":"53","a":"71","s":"107","ss":"124","sss":""},
    {"f":"3","e":"16","d":"19","c":"35","b":"57","a":"75","s":"88","ss":"118","sss":""},
    {"f":"3","e":"16","d":"27","c":"35","b":"57","a":"69","s":"93","ss":"","sss":""},
    {"f":"3","e":"16","d":"27","c":"35","b":"57","a":"78","s":"92","ss":"113","sss":"136"},
    {"f":"3","e":"16","d":"27","c":"35","b":"57","a":"89","s":"89","ss":"","sss":""},
    {"f":"3","e":"16","d":"27","c":"32","b":"53","a":"71","s":"107","ss":"120","sss":""},
    {"f":"3","e":"16","d":"27","c":"32","b":"53","a":"71","s":"107","ss":"124","sss":""},
    {"f":"3","e":"16","d":"27","c":"32","b":"53","a":"75","s":"88","ss":"118","sss":""},
    {"f":"3","e":"16","d":"27","c":"32","b":"52","a":"75","s":"88","ss":"118","sss":""},
    {"f":"3","e":"16","d":"27","c":"32","b":"52","a":"72","s":"100","ss":"133","sss":""},
    {"f":"3","e":"16","d":"27","c":"32","b":"61","a":"78","s":"92","ss":"113","sss":"136"},
    {"f":"3","e":"16","d":"27","c":"32","b":"61","a":"81","s":"105","ss":"117","sss":"128"},
    {"f":"3","e":"8","d":"27","c":"35","b":"57","a":"69","s":"93","ss":"","sss":""},
    {"f":"3","e":"8","d":"27","c":"35","b":"57","a":"78","s":"92","ss":"113","sss":"136"},
    {"f":"3","e":"8","d":"27","c":"35","b":"57","a":"89","s":"89","ss":"","sss":""},
    {"f":"3","e":"8","d":"27","c":"35","b":"53","a":"71","s":"107","ss":"120","sss":""},
    {"f":"3","e":"8","d":"27","c":"35","b":"53","a":"71","s":"107","ss":"124","sss":""},
    {"f":"3","e":"8","d":"27","c":"35","b":"53","a":"75","s":"88","ss":"118","sss":""},
    {"f":"3","e":"8","d":"27","c":"32","b":"52","a":"75","s":"88","ss":"118","sss":""},
    {"f":"3","e":"8","d":"27","c":"32","b":"52","a":"72","s":"100","ss":"133","sss":""},
    {"f":"3","e":"8","d":"27","c":"32","b":"61","a":"78","s":"92","ss":"113","sss":"136"},
    {"f":"3","e":"8","d":"27","c":"32","b":"61","a":"81","s":"105","ss":"117","sss":"128"},
    {"f":"3","e":"8","d":"21","c":"29","b":"54","a":"81","s":"105","ss":"117","sss":"128"},
    {"f":"3","e":"8","d":"21","c":"29","b":"54","a":"84","s":"105","ss":"117","sss":"128"},
    {"f":"3","e":"8","d":"21","c":"29","b":"54","a":"84","s":"138","ss":"","sss":""},
    {"f":"3","e":"8","d":"21","c":"29","b":"56","a":"67","s":"92","ss":"113","sss":"136"},
    {"f":"3","e":"8","d":"21","c":"29","b":"56","a":"69","s":"93","ss":"","sss":""},
    {"f":"3","e":"8","d":"21","c":"40","b":"57","a":"69","s":"93","ss":"","sss":""},
    {"f":"3","e":"8","d":"21","c":"40","b":"57","a":"78","s":"92","ss":"113","sss":"136"},
    {"f":"3","e":"8","d":"21","c":"40","b":"57","a":"89","s":"89","ss":"","sss":""},
    {"f":"3","e":"8","d":"21","c":"40","b":"49","a":"72","s":"100","ss":"133","sss":""},
    {"f":"3","e":"8","d":"21","c":"40","b":"49","a":"76","s":"104","ss":"125","sss":""},
    
    {"f":"4","e":"10","d":"21","c":"29","b":"56","a":"67","s":"92","ss":"113","sss":"136"},
    {"f":"4","e":"10","d":"21","c":"29","b":"56","a":"69","s":"93","ss":"","sss":""},
    {"f":"4","e":"10","d":"21","c":"40","b":"57","a":"69","s":"93","ss":"","sss":""},
    {"f":"4","e":"10","d":"21","c":"40","b":"57","a":"78","s":"92","ss":"113","sss":"136"},
    {"f":"4","e":"10","d":"21","c":"40","b":"57","a":"89","s":"89","ss":"","sss":""},
    {"f":"4","e":"10","d":"21","c":"40","b":"49","a":"76","s":"104","ss":"125","sss":""},
    {"f":"4","e":"10","d":"21","c":"40","b":"49","a":"72","s":"100","ss":"133","sss":""},
    {"f":"4","e":"10","d":"24","c":"34","b":"52","a":"72","s":"100","ss":"133","sss":""},
    {"f":"4","e":"10","d":"24","c":"34","b":"52","a":"75","s":"88","ss":"118","sss":""},
    {"f":"4","e":"10","d":"24","c":"38","b":"48","a":"91","s":"91","ss":"","sss":""},
    {"f":"4","e":"10","d":"24","c":"38","b":"48","a":"72","s":"100","ss":"133","sss":""},
    {"f":"4","e":"10","d":"24","c":"38","b":"49","a":"72","s":"100","ss":"133","sss":""},
    {"ps":"*","f":"4","e":"10","d":"24","c":"38","b":"49","a":"76","s":"104","ss":"125","sss":""},
    {"f":"4","e":"12","d":"24","c":"34","b":"52","a":"72","s":"100","ss":"133","sss":""},
    {"f":"4","e":"12","d":"24","c":"34","b":"52","a":"75","s":"88","ss":"118","sss":""},
    {"f":"4","e":"12","d":"24","c":"38","b":"48","a":"91","s":"91","ss":"","sss":""},
    {"f":"4","e":"12","d":"24","c":"38","b":"48","a":"72","s":"100","ss":"133","sss":""},
    {"f":"4","e":"12","d":"24","c":"38","b":"49","a":"72","s":"100","ss":"133","sss":""},
    {"f":"4","e":"12","d":"24","c":"38","b":"49","a":"76","s":"104","ss":"125","sss":""},
    {"f":"4","e":"12","d":"22","c":"38","b":"48","a":"91","s":"91","ss":"","sss":""},
    {"f":"4","e":"12","d":"22","c":"38","b":"48","a":"72","s":"100","ss":"133","sss":""},
    {"f":"4","e":"12","d":"22","c":"38","b":"49","a":"72","s":"100","ss":"133","sss":""},
    {"f":"4","e":"12","d":"22","c":"38","b":"49","a":"76","s":"104","ss":"125","sss":""},
    {"f":"4","e":"12","d":"22","c":"33","b":"63","a":"85","s":"90","ss":"123","sss":""},
    {"f":"4","e":"12","d":"22","c":"33","b":"63","a":"66","s":"97","ss":"122","sss":""},
    {"f":"4","e":"12","d":"22","c":"33","b":"63","a":"66","s":"137","ss":"","sss":""},
    {"f":"4","e":"12","d":"22","c":"33","b":"59","a":"74","s":["106","99"],"ss":"","sss":""},
    {"f":"4","e":"12","d":"22","c":"33","b":"59","a":"74","s":["106","109"],"ss":"","sss":""},
    {"f":"4","e":"15","d":"22","c":"38","b":"48","a":"91","s":"91","ss":"","sss":""},
    {"f":"4","e":"15","d":"22","c":"38","b":"48","a":"72","s":"100","ss":"133","sss":""},
    {"f":"4","e":"15","d":"22","c":"38","b":"49","a":"72","s":"100","ss":"133","sss":""},
    {"f":"4","e":"15","d":"22","c":"38","b":"49","a":"76","s":"104","ss":"125","sss":""},
    {"f":"4","e":"15","d":"22","c":"33","b":"63","a":"85","s":"90","ss":"123","sss":""},
    {"f":"4","e":"15","d":"22","c":"33","b":"63","a":"66","s":"97","ss":"122","sss":""},
    {"f":"4","e":"15","d":"22","c":"33","b":"63","a":"66","s":"137","ss":"","sss":""},
    {"f":"4","e":"15","d":"22","c":"33","b":"59","a":"74","s":["106","99"],"ss":"","sss":""},
    {"f":"4","e":"15","d":"22","c":"33","b":"59","a":"74","s":["106","109"],"ss":"","sss":""},
    {"f":"4","e":"15","d":"20","c":"30","b":"50","a":"80","s":"96","ss":"115","sss":""},
    {"f":"4","e":"15","d":"20","c":"30","b":"61","a":"78","s":"92","ss":"113","sss":"136"},
    {"f":"4","e":"15","d":"20","c":"30","b":"61","a":"81","s":"105","ss":"117","sss":"128"},
    {"f":"4","e":"15","d":"20","c":"31","b":"54","a":"81","s":"105","ss":"117","sss":"128"},
    {"f":"4","e":"15","d":"20","c":"31","b":"54","a":"84","s":"105","ss":"117","sss":"128"},
    {"f":"4","e":"15","d":"20","c":"31","b":"54","a":"84","s":"138","ss":"","sss":""},
    
    {"f":"5","e":"7","d":"25","c":"33","b":"63","a":"85","s":"90","ss":"123","sss":""},
    {"f":"5","e":"7","d":"25","c":"33","b":"63","a":"66","s":"97","ss":"122","sss":""},
    {"f":"5","e":"7","d":"25","c":"33","b":"63","a":"66","s":"137","ss":"","sss":""},
    {"f":"5","e":"7","d":"25","c":"33","b":"59","a":"74","s":["106","99"],"ss":"","sss":""},
    {"f":"5","e":"7","d":"25","c":"33","b":"59","a":"74","s":["106","109"],"ss":"","sss":""},
    {"f":"5","e":"7","d":"25","c":["36","47"],"b":"59","a":"74","s":["106","99"],"ss":"","sss":""},
    {"f":"5","e":"7","d":"25","c":["36","47"],"b":"59","a":"74","s":["106","109"],"ss":"","sss":""},
    {"f":"5","e":"7","d":"25","c":["36","47"],"b":"62","a":"82","s":"110","ss":"116","sss":"127"},
    {"f":"5","e":"7","d":"25","c":["36","47"],"b":"62","a":"82","s":"86","ss":"126","sss":"129"},
    {"f":"5","e":"7","d":"18","c":"44","b":"60","a":"66","s":"97","ss":"122","sss":""},
    {"f":"5","e":"7","d":"18","c":"44","b":"60","a":"66","s":"137","ss":"","sss":""},
    {"f":"5","e":"7","d":"18","c":"44","b":"60","a":"102","s":"102","ss":"","sss":""},
    {"f":"5","e":"7","d":"18","c":"44","b":"61","a":"78","s":"92","ss":"113","sss":"136"},
    {"f":"5","e":"7","d":"18","c":"44","b":"61","a":"81","s":"105","ss":"117","sss":"128"},
    {"f":"5","e":"7","d":"18","c":"31","b":"54","a":"81","s":"105","ss":"117","sss":"128"},
    {"f":"5","e":"7","d":"18","c":"31","b":"54","a":"84","s":"105","ss":"117","sss":"128"},
    {"f":"5","e":"7","d":"18","c":"31","b":"54","a":"84","s":"138","ss":"","sss":""},
    {"f":"5","e":"14","d":"18","c":"44","b":"60","a":"66","s":"97","ss":"122","sss":""},
    {"f":"5","e":"14","d":"18","c":"44","b":"60","a":"66","s":"137","ss":"","sss":""},
    {"f":"5","e":"14","d":"18","c":"44","b":"60","a":"102","s":"102","ss":"","sss":""},
    {"f":"5","e":"14","d":"18","c":"44","b":"61","a":"78","s":"92","ss":"113","sss":"136"},
    {"f":"5","e":"14","d":"18","c":"44","b":"61","a":"81","s":"105","ss":"117","sss":"128"},
    {"f":"5","e":"14","d":"18","c":"31","b":"54","a":"81","s":"105","ss":"117","sss":"128"},
    {"f":"5","e":"14","d":"18","c":"31","b":"54","a":"84","s":"105","ss":"117","sss":"128"},
    {"f":"5","e":"14","d":"18","c":"31","b":"54","a":"84","s":"138","ss":"","sss":""},
    {"f":"5","e":"14","d":"20","c":"31","b":"54","a":"81","s":"105","ss":"117","sss":"128"},
    {"f":"5","e":"14","d":"20","c":"31","b":"54","a":"84","s":"105","ss":"117","sss":"128"},
    {"f":"5","e":"14","d":"20","c":"31","b":"54","a":"84","s":"138","ss":"","sss":""},
    {"f":"5","e":"14","d":"20","c":"30","b":"61","a":"81","s":"105","ss":"117","sss":"128"},
    {"f":"5","e":"14","d":"20","c":"30","b":"61","a":"78","s":"92","ss":"113","sss":"136"},
    {"f":"5","e":"14","d":"20","c":"30","b":"50","a":"80","s":"96","ss":"115","sss":""},
    {"f":"5","e":"14","d":"28","c":"30","b":"61","a":"81","s":"105","ss":"117","sss":"128"},
    {"f":"5","e":"14","d":"28","c":"30","b":"61","a":"78","s":"92","ss":"113","sss":"136"},
    {"f":"5","e":"14","d":"28","c":"30","b":"50","a":"80","s":"96","ss":"115","sss":""},
    {"f":"5","e":"14","d":"28","c":"39","b":"53","a":"71","s":"107","ss":"120","sss":""},
    {"f":"5","e":"14","d":"28","c":"39","b":"53","a":"71","s":"107","ss":"124","sss":""},
    {"f":"5","e":"14","d":"28","c":"39","b":"53","a":"75","s":"88","ss":"118","sss":""},
    {"f":"5","e":"14","d":"28","c":"39","b":"65","a":"65","s":"103","ss":"134","sss":""},
    {"f":"5","e":"9","d":"28","c":"30","b":"61","a":"81","s":"105","ss":"117","sss":"128"},
    {"f":"5","e":"9","d":"28","c":"30","b":"61","a":"78","s":"92","ss":"113","sss":"136"},
    {"f":"5","e":"9","d":"28","c":"30","b":"50","a":"80","s":"96","ss":"115","sss":""},
    {"f":"5","e":"9","d":"28","c":"39","b":"53","a":"71","s":"107","ss":"120","sss":""},
    {"f":"5","e":"9","d":"28","c":"39","b":"53","a":"71","s":"107","ss":"124","sss":""},
    {"f":"5","e":"9","d":"28","c":"39","b":"53","a":"75","s":"88","ss":"118","sss":""},
    {"f":"5","e":"9","d":"28","c":"39","b":"65","a":"65","s":"103","ss":"134","sss":""},
    {"f":"5","e":"9","d":"26","c":"41","b":"70","a":"70","s":"","ss":"","sss":""},
    {"f":"5","e":"9","d":"26","c":"37","b":"51","a":"73","s":"95","ss":"135","sss":""},
    {"f":"5","e":"9","d":"26","c":"46","b":"58","a":"80","s":"96","ss":"115","sss":""},
    {"f":"5","e":"9","d":"26","c":"46","b":"58","a":"94","s":"94","ss":"121","sss":""},
    {"f":"5","e":"9","d":"26","c":"46","b":"58","a":"94","s":"94","ss":"131","sss":"132"},
    {"f":"5","e":"9","d":"26","c":"46","b":"60","a":"66","s":"97","ss":"122","sss":""},
    {"f":"5","e":"9","d":"26","c":"46","b":"60","a":"66","s":"137","ss":"","sss":""},
    {"f":"5","e":"9","d":"26","c":"46","b":"60","a":"102","s":"102","ss":"","sss":""},
    {"f":"5","e":"9","d":"26","c":"46","b":"48","a":"72","s":"100","ss":"133","sss":""},
    {"f":"5","e":"9","d":"26","c":"46","b":"48","a":"91","s":"91","ss":"","sss":""},
    {"f":"5","e":"9","d":"26","c":"43","b":"77","a":"77","s":"108","ss":"112","sss":""},
    {"f":"5","e":"9","d":"26","c":"43","b":"77","a":"77","s":"98","ss":"111","sss":""},
    {"f":"5","e":"9","d":"26","c":"43","b":"55","a":"68","s":"101","ss":"119","sss":""},
    {"f":"5","e":"9","d":"26","c":"43","b":"55","a":"68","s":"101","ss":"114","sss":""},
    {"f":"5","e":"9","d":"26","c":"43","b":"55","a":["68","79"],"s":"","ss":"","sss":""},
    {"f":"5","e":"9","d":"26","c":"43","b":"55","a":"85","s":"90","ss":"123","sss":""},
    {"f":"5","e":"13","d":"26","c":"41","b":"70","a":"70","s":"","ss":"","sss":""},
    {"f":"5","e":"13","d":"26","c":"37","b":"51","a":"73","s":"95","ss":"135","sss":""},
    {"f":"5","e":"13","d":"26","c":"46","b":"58","a":"80","s":"96","ss":"115","sss":""},
    {"f":"5","e":"13","d":"26","c":"46","b":"58","a":"94","s":"94","ss":"121","sss":""},
    {"f":"5","e":"13","d":"26","c":"46","b":"58","a":"94","s":"94","ss":"131","sss":"132"},
    {"f":"5","e":"13","d":"26","c":"46","b":"60","a":"66","s":"97","ss":"122","sss":""},
    {"f":"5","e":"13","d":"26","c":"46","b":"60","a":"66","s":"137","ss":"","sss":""},
    {"f":"5","e":"13","d":"26","c":"46","b":"60","a":"102","s":"102","ss":"","sss":""},
    {"f":"5","e":"13","d":"26","c":"46","b":"48","a":"72","s":"100","ss":"133","sss":""},
    {"f":"5","e":"13","d":"26","c":"46","b":"48","a":"91","s":"91","ss":"","sss":""},
    {"f":"5","e":"13","d":"26","c":"43","b":"77","a":"77","s":"108","ss":"112","sss":""},
    {"f":"5","e":"13","d":"26","c":"43","b":"77","a":"77","s":"98","ss":"111","sss":""},
    {"f":"5","e":"13","d":"26","c":"43","b":"55","a":"68","s":"101","ss":"119","sss":""},
    {"f":"5","e":"13","d":"26","c":"43","b":"55","a":"68","s":"101","ss":"114","sss":""},
    {"f":"5","e":"13","d":"26","c":"43","b":"55","a":["68","79"],"s":"","ss":"","sss":""},
    {"f":"5","e":"13","d":"26","c":"43","b":"55","a":"85","s":"90","ss":"123","sss":""},
    {"f":"5","e":"13","d":"17","c":"43","b":"77","a":"77","s":"108","ss":"112","sss":""},
    {"f":"5","e":"13","d":"17","c":"43","b":"77","a":"77","s":"98","ss":"111","sss":""},
    {"f":"5","e":"13","d":"17","c":"43","b":"55","a":"68","s":"101","ss":"119","sss":""},
    {"f":"5","e":"13","d":"17","c":"43","b":"55","a":"68","s":"101","ss":"114","sss":""},
    {"f":"5","e":"13","d":"17","c":"43","b":"55","a":["68","79"],"s":"","ss":"","sss":""},
    {"f":"5","e":"13","d":"17","c":"43","b":"55","a":"85","s":"90","ss":"123","sss":""},
    {"f":"5","e":"13","d":"17","c":"45","b":"55","a":"85","s":"90","ss":"123","sss":""},
    {"f":"5","e":"13","d":"17","c":"64","b":"64","a":"83","s":"87","ss":"","sss":""},
    
    {"f":"6","e":"11","d":"23","c":"42","b":"62","a":"82","s":"110","ss":"116","sss":"127"},
    {"f":"6","e":"11","d":"23","c":"42","b":"62","a":"82","s":"110","ss":"116","sss":"127"},
    {"f":"6","e":"11","d":"23","c":"47","b":"62","a":"82","s":"86","ss":"126","sss":"129"},
    {"f":"6","e":"11","d":"23","c":"47","b":"62","a":"82","s":"86","ss":"126","sss":"129"},
    {"f":"6","e":"11","d":"23","c":"47","b":"59","a":"74","s":["106","99"],"ss":"","sss":""},
    {"f":"6","e":"11","d":"23","c":"47","b":"59","a":"74","s":["106","109"],"ss":"","sss":""},
    
    {"f":"139","e":"140","d":"141","c":"142","b":"143","a":"143","s":"144","ss":"","sss":""},
    {"f":"139","e":"140","d":"141","c":"142","b":"143","a":"143","s":"145","ss":"146","sss":""}
]}
